megad/__init__.py
megad/alembic/README
megad/alembic/env.py
megad/alembic/script.py.mako
megad/alembic/versions/2023_10_09_1553-f8838525b28f_.py
megad/alembic/versions/2023_10_09_1556-7df91f723f2d_.py
megad/alembic/versions/2023_10_09_1602-2dde7648bb3f_.py
megad/alembic/versions/2023_10_09_1605-a6fd63177145_.py
megad/alembic/versions/2023_10_09_2058-37fe8c30dde1_.py
megad/alembic/versions/2023_10_11_2050-378d1b2bf905_.py
megad/backup.py
megad/config.py
megad/core.py
megad/db/__init__.py
megad/db/base.py
megad/db/engine.py
megad/db/objects.py
megad/firmware/upgrade.py
megad/parsers/__init__.py
megad/parsers/base.py
megad/parsers/cache.py
megad/parsers/config.py
megad/parsers/const.py
megad/parsers/enums.py
megad/parsers/i2c_sensors.py
megad/parsers/main.py
megad/parsers/objects.py
megad/parsers/param_desc.py
megad/parsers/poly.py
megad/parsers/proto.py
megad/parsers/tools.py
megad/parsers/units.py
megad/scan.py
megad/srv/__init__.py
megad/srv/cache/__init__.py
megad/srv/cache/core.py
megad/srv/cache/dlist.py
megad/srv/cache/lru.py
megad/srv/errors.py
megad/srv/main.py
megad/srv/router.py
megad_lib-2.1.0.dist-info/METADATA
megad_lib-2.1.0.dist-info/WHEEL
megad_lib-2.1.0.dist-info/RECORD
