Metadata-Version: 2.1
Name: megad-lib
Version: 2.1.0
Summary: 
Author: Your Name
Author-email: you@example.com
Requires-Python: >=3.11,<4.0
Classifier: Programming Language :: Python :: 3
Classifier: Programming Language :: Python :: 3.11
Classifier: Programming Language :: Python :: 3.12
Requires-Dist: aiohttp (>=1.1)
Requires-Dist: aiosqlite (>=0.19.0,<0.20.0)
Requires-Dist: alembic (>=1.12.0,<2.0.0)
Requires-Dist: beautifulsoup4 (>=4,<5)
Requires-Dist: cashews (>=6.3.0,<7.0.0)
Requires-Dist: intelhex (>=2.3.0,<3.0.0)
Requires-Dist: orjson (>=3.9.7,<4.0.0)
Requires-Dist: pydantic (<2)
Requires-Dist: sqlalchemy (>=2.0.21,<3.0.0)
